dqchecks/__init__.py
dqchecks/exceptions.py
dqchecks/file_loader.py
dqchecks/panacea.py
dqchecks/proteus.py
dqchecks/qa.py
dqchecks/transforms.py
dqchecks/utils.py
dqchecks/_jar/__init__.py
dqchecks/_jar/mytool.jar
dqchecks/tests/__init__.py
dqchecks/tests/test_check_formula_errors.py
dqchecks/tests/test_check_sheet_structure.py
dqchecks/tests/test_check_value_in_cell.py
dqchecks/tests/test_clean_formula_spaces_in_workbook.py
dqchecks/tests/test_compare_formulas.py
dqchecks/tests/test_create_dataframe_from_company_acronym_check.py
dqchecks/tests/test_create_dataframe_missing_sheets.py
dqchecks/tests/test_create_missing_sheet_row.py
dqchecks/tests/test_create_nulls_in_measure_validation_event.py
dqchecks/tests/test_create_process_model_mapping_validation_event.py
dqchecks/tests/test_create_same_boncode_diff_desc_validation_event.py
dqchecks/tests/test_create_same_desc_diff_boncode_validation_event.py
dqchecks/tests/test_create_validation_event_row_dataframe.py
dqchecks/tests/test_file_loader.py
dqchecks/tests/test_find_formula_differences.py
dqchecks/tests/test_find_formula_errors.py
dqchecks/tests/test_find_missing_sheets.py
dqchecks/tests/test_find_pk_errors.py
dqchecks/tests/test_find_shape_differences.py
dqchecks/tests/test_is_valid_regex.py
dqchecks/tests/test_process_fout_sheets.py
dqchecks/tests/test_process_sheet.py
dqchecks/tests/test_qa.py
dqchecks/tests/test_simple_hdfs_ls.py
dqchecks/tests/test_validate_tabs_between_spreadsheets.py
ofwat_dqchecks-0.1.8.dist-info/licenses/LICENSE
ofwat_dqchecks-0.1.8.dist-info/METADATA
ofwat_dqchecks-0.1.8.dist-info/WHEEL
ofwat_dqchecks-0.1.8.dist-info/top_level.txt
ofwat_dqchecks-0.1.8.dist-info/RECORD
