Metadata-Version: 2.4
Name: ofwat-dqchecks
Version: 0.1.8
Summary: Excel validations
Home-page: https://github.com/Ofwat/dqchecks
Author: Ofwat
Project-URL: Source, https://github.com/Ofwat/dqchecks
Project-URL: Tracker, https://github.com/Ofwat/dqchecks/issues
Keywords: excel data validation
License-File: LICENSE
Requires-Dist: openpyxl>=3.1.2
Requires-Dist: pandas>=1.5.0
Requires-Dist: numpy
Dynamic: author
Dynamic: description
Dynamic: description-content-type
Dynamic: home-page
Dynamic: keywords
Dynamic: license-file
Dynamic: project-url
Dynamic: requires-dist
Dynamic: summary
